{
	"geode": "2.0.0-beta.23",
	"gd": "2.204",
	"version": "v1.0.0-alpha.1",
	"id": "bigmancozmo.spacemenu",
	"name": "Space Menu",
	"developer": "Bigmancozmo",
	"description": "",
	"resources": {
		"spritesheets": {
			"SM_Sheet": [
				"res/logos/*.png",
				"res/hearts/*.png",
				"res/*.png"
			]
		},
		"files": [
			"res/fonts-fixed/*.png",
			"res/fonts-fixed/*.fnt"
		]
	},
	"dependencies": [
		{
			"id": "geode.node-ids",
			"version": ">=v1.8.0",
			"importance": "required"
		},
		{
			"id": "geode.custom-keybinds",
			"version": ">=1.5.2",
			"importance": "required",
			"platforms":  ["windows"]
		}
	]
}